prettiest_ast/__init__.py
prettiest_ast/prettiest_ast.py
prettiest_ast-0.0.1.dev4.dist-info/LICENSE
prettiest_ast-0.0.1.dev4.dist-info/METADATA
prettiest_ast-0.0.1.dev4.dist-info/WHEEL
prettiest_ast-0.0.1.dev4.dist-info/top_level.txt
prettiest_ast-0.0.1.dev4.dist-info/RECORD
