Metadata-Version: 2.1
Name: prettiest-ast
Version: 0.0.1.dev4
Summary: a pretty printer for abstract syntax trees
Home-page: https://github.com/salt-die/prettiest_ast
Author: salt-die
Author-email: saltdie.py@gmail.com
License: MIT
Platform: UNKNOWN
